ocelastic/__init__.py
ocelastic/core.py
tests/__init__.py
tests/test_enet_convex_hull.py
tests/test_threshold_finder.py
oneclass_elasticnet-0.0.1.dist-info/LICENSE
oneclass_elasticnet-0.0.1.dist-info/METADATA
oneclass_elasticnet-0.0.1.dist-info/WHEEL
oneclass_elasticnet-0.0.1.dist-info/top_level.txt
oneclass_elasticnet-0.0.1.dist-info/RECORD
