Metadata-Version: 2.2
Name: oneclass-elasticnet
Version: 0.0.1
Summary: A package for anomaly detection using Elastic Net and Convex Hull.
Home-page: https://github.com/YousofLHC/flexi_datareader
Author: Yousof Ghalenoei
Author-email: yousof.ghalenoei2017@gmail.com
Classifier: Programming Language :: Python :: 3
Classifier: License :: OSI Approved :: MIT License
Classifier: Operating System :: OS Independent
Classifier: Intended Audience :: Developers
Classifier: Topic :: Software Development :: Libraries :: Python Modules
Requires-Python: >=3.7
License-File: LICENSE
Requires-Dist: scikit-learn>=1.6.1
Requires-Dist: numpy>=1.26.4
Requires-Dist: qpsolvers>=4.3.1
Requires-Dist: tqdm>=4.66.2
Dynamic: author
Dynamic: author-email
Dynamic: classifier
Dynamic: description
Dynamic: description-content-type
Dynamic: home-page
Dynamic: requires-dist
Dynamic: requires-python
Dynamic: summary
